mathforuni/__init__.py
mathforuni/graphs.py
mathforuni/probability.py
mathforuni/test_graph.py
mathforuni/test_probability.py
mathforuni-0.1.0.dist-info/METADATA
mathforuni-0.1.0.dist-info/WHEEL
mathforuni-0.1.0.dist-info/RECORD
