Metadata-Version: 2.4
Name: mathforuni
Version: 0.1.0
Summary: Описание вашей библиотеки
Classifier: License :: OSI Approved :: MIT License
Classifier: Operating System :: OS Independent
Classifier: Programming Language :: Python :: 3
Requires-Python: >=3.6
